linkhut_cli/__init__.py
linkhut_cli/__main__.py
linkhut_cli/cli.py
linkhut_cli/utils.py
linkhut_cli-0.2.1.dist-info/METADATA
linkhut_cli-0.2.1.dist-info/WHEEL
linkhut_cli-0.2.1.dist-info/entry_points.txt
linkhut_cli-0.2.1.dist-info/licenses/LICENSE
linkhut_cli-0.2.1.dist-info/RECORD
