Metadata-Version: 2.4
Name: linkhut-cli
Version: 0.2.1
Summary: beautiful TUI to manage your bookmarks stored on linkhut
Project-URL: Repository, https://github.com/shubxam/linkhut-cli
Author-email: Shubham Soni <shubxam@gmail.com>
License-Expression: MIT
License-File: LICENSE
Keywords: bookmark-manager,bookmarks,tui
Classifier: Development Status :: 4 - Beta
Classifier: Intended Audience :: Developers
Classifier: Operating System :: OS Independent
Classifier: Programming Language :: Python
Classifier: Programming Language :: Python :: 3
Classifier: Programming Language :: Python :: 3.11
Classifier: Programming Language :: Python :: 3.12
Classifier: Programming Language :: Python :: 3.13
Classifier: Typing :: Typed
Requires-Python: <4.0,>=3.11
Requires-Dist: dotenv>=0.9.9
Requires-Dist: httpx>=0.28.1
Requires-Dist: loguru>=0.7.3
Requires-Dist: tqdm>=4.67.1
Requires-Dist: typer>=0.15.3
